evergreen_p_convolve/__init__.py
evergreen_p_convolve/_p_convolve.so
evergreen_p_convolve/p_convolve.py
evergreen_p_convolve-1.0.3.dist-info/LICENSE
evergreen_p_convolve-1.0.3.dist-info/METADATA
evergreen_p_convolve-1.0.3.dist-info/WHEEL
evergreen_p_convolve-1.0.3.dist-info/top_level.txt
evergreen_p_convolve-1.0.3.dist-info/RECORD
