Metadata-Version: 2.1
Name: evergreen-p-convolve
Version: 1.0.3
Summary: A python p_convolve package based on evergreenforest
Home-page: https://github.com/SeanSRice/evergreen_fft.git
Author: Rice
Author-email: mrseanrice@gmail.com
License: UNKNOWN
Platform: UNKNOWN
Classifier: Programming Language :: Python :: 2.7
Classifier: License :: OSI Approved :: MIT License
